neuroqc/__init__.py
neuroqc/neuroqc.py
neuroqc-0.1.0.dist-info/DESCRIPTION.rst
neuroqc-0.1.0.dist-info/METADATA
neuroqc-0.1.0.dist-info/RECORD
neuroqc-0.1.0.dist-info/WHEEL
neuroqc-0.1.0.dist-info/metadata.json
neuroqc-0.1.0.dist-info/top_level.txt
